chorokit/__init__.py
chorokit/api.py
chorokit/classify.py
chorokit/cli.py
chorokit/legend.py
chorokit/palettes.py
chorokit/projection.py
chorokit/style.py
chorokit-0.1.0.dist-info/METADATA
chorokit-0.1.0.dist-info/WHEEL
chorokit-0.1.0.dist-info/entry_points.txt
chorokit-0.1.0.dist-info/licenses/LICENSE
chorokit-0.1.0.dist-info/RECORD
