Metadata-Version: 2.4
Name: chorokit
Version: 0.1.0
Summary: Choropleth helper for GeoPandas with clean defaults for projection, layout and legend
Project-URL: Homepage, https://github.com/mstiles/chorokit
Author: Matt Stiles
License: MIT
License-File: LICENSE
Requires-Python: >=3.10
Requires-Dist: geopandas>=0.14
Requires-Dist: mapclassify>=2.6
Requires-Dist: matplotlib>=3.7
Requires-Dist: pyproj>=3.6
Requires-Dist: shapely>=2.0
